ayaka_games/__init__.py
ayaka_games/bag/__init__.py
ayaka_games/bag/bag.py
ayaka_games/bag/reputation.py
ayaka_games/calculate/__init__.py
ayaka_games/calculate/calculate.py
ayaka_games/calculate/reputation.py
ayaka_games/checkin/__init__.py
ayaka_games/checkin/checkin.py
ayaka_games/checkin/reputation.py
ayaka_games/cy_query.py
ayaka_games/dragon.py
ayaka_games/genshin_random_event.py
ayaka_games/get_30.py
ayaka_games/incan.py
ayaka_games/mana.py
ayaka_games/plus_one.py
ayaka_games/pray/__init__.py
ayaka_games/pray/pray.py
ayaka_games/pray/reputation.py
ayaka_games/requirements.txt
ayaka_games/utils/__init__.py
ayaka_games/utils/config.py
ayaka_games/utils/download.py
ayaka_games/utils/reputation.py
ayaka_games/utils/subscribe.py
ayaka_games/who_is_suspect.py
ayaka_games/word_tax.py
ayaka_games-0.4.1.dist-info/LICENSE
ayaka_games-0.4.1.dist-info/METADATA
ayaka_games-0.4.1.dist-info/WHEEL
ayaka_games-0.4.1.dist-info/RECORD
