Metadata-Version: 2.1
Name: ayaka-games
Version: 0.4.1
Summary: ayaka小游戏合集
Home-page: https://github.com/bridgeL/ayaka_games
License: MIT
Author: Su
Author-email: wxlxy316@163.com
Requires-Python: >=3.10,<4.0
Classifier: License :: OSI Approved :: MIT License
Classifier: Programming Language :: Python :: 3
Classifier: Programming Language :: Python :: 3.10
Classifier: Programming Language :: Python :: 3.11
Requires-Dist: ayaka (>=0.0.4.0,<0.0.5.0)
Requires-Dist: pypinyin (>=0.47.1)
Project-URL: Repository, https://github.com/bridgeL/ayaka_games
